CHANGES.txt
README.txt
bootstrap.py
buildout.cfg
setup.py
src/z3c/__init__.py
src/z3c.jsontree.egg-info/PKG-INFO
src/z3c.jsontree.egg-info/SOURCES.txt
src/z3c.jsontree.egg-info/dependency_links.txt
src/z3c.jsontree.egg-info/namespace_packages.txt
src/z3c.jsontree.egg-info/not-zip-safe
src/z3c.jsontree.egg-info/requires.txt
src/z3c.jsontree.egg-info/top_level.txt
src/z3c/jsontree/README.txt
src/z3c/jsontree/__init__.py
src/z3c/jsontree/base.py
src/z3c/jsontree/configure.zcml
src/z3c/jsontree/interfaces.py
src/z3c/jsontree/jsonrpc.py
src/z3c/jsontree/jsonrpc.zcml
src/z3c/jsontree/subitem.py
src/z3c/jsontree/tests.py
src/z3c/jsontree/util.py
src/z3c/jsontree/browser/__init__.py
src/z3c/jsontree/browser/configure.zcml
src/z3c/jsontree/browser/li.pt
src/z3c/jsontree/browser/tree.pt
src/z3c/jsontree/browser/tree.py
src/z3c/jsontree/browser/ul.pt
src/z3c/jsontree/browser/z3c.jsontree.css
src/z3c/jsontree/browser/img/z3cJSONTreeCollapsed.gif
src/z3c/jsontree/browser/img/z3cJSONTreeExpanded.gif
src/z3c/jsontree/browser/img/z3cJSONTreeStatic.gif
src/z3c/jsontree/browser/js/z3c.jsontree-0.5.0.js
src/z3c/jsontree/browser/tests/__init__.py
src/z3c/jsontree/browser/tests/test_view.py
src/z3c/jsontree/browser/tests/util.py
src/z3c/jsontree/browser/tests/output/tree_1.txt
src/z3c/jsontree/browser/tests/output/tree_2.txt
src/z3c/jsontree/browser/tests/output/tree_3.txt